{
  "signals": [
    {
      "id": 2,
      "direction": "down",
      "upNeigh": 3,
      "downNeigh": 1
    },
    {
      "id": 5,
      "direction": "down",
      "upNeigh": 17,
      "downNeigh": 4
    },
    {
      "id": 6,
      "direction": "down",
      "upNeigh": 14,
      "downNeigh": 4
    },
    {
      "id": 8,
      "direction": "down",
      "upNeigh": 9,
      "downNeigh": 7
    },
    {
      "id": 10,
      "direction": "down",
      "upNeigh": 11,
      "downNeigh": 7
    },
    {
      "id": 12,
      "direction": "up",
      "upNeigh": 13,
      "downNeigh": 11
    },
    {
      "id": 15,
      "direction": "up",
      "upNeigh": 13,
      "downNeigh": 34
    },
    {
      "id": 18,
      "direction": "up",
      "upNeigh": 20,
      "downNeigh": 9
    },
    {
      "id": 22,
      "direction": "down",
      "upNeigh": 29,
      "downNeigh": 21
    },
    {
      "id": 23,
      "direction": "down",
      "upNeigh": 40,
      "downNeigh": 21
    },
    {
      "id": 25,
      "direction": "up",
      "upNeigh": 26,
      "downNeigh": 14
    },
    {
      "id": 27,
      "direction": "up",
      "upNeigh": 26,
      "downNeigh": 28
    },
    {
      "id": 31,
      "direction": "up",
      "upNeigh": 30,
      "downNeigh": 29
    },
    {
      "id": 32,
      "direction": "up",
      "upNeigh": 30,
      "downNeigh": 33
    },
    {
      "id": 35,
      "direction": "down",
      "upNeigh": 33,
      "downNeigh": 36
    },
    {
      "id": 38,
      "direction": "down",
      "upNeigh": 39,
      "downNeigh": 36
    }
  ],
  "sections": [
    {
      "id": 1,
      "upNeigh": 2,
      "downNeigh": 0
    },
    {
      "id": 3,
      "upNeigh": 4,
      "downNeigh": 2
    },
    {
      "id": 17,
      "upNeigh": 7,
      "downNeigh": 5
    },
    {
      "id": 14,
      "upNeigh": 25,
      "downNeigh": 6
    },
    {
      "id": 9,
      "upNeigh": 18,
      "downNeigh": 8
    },
    {
      "id": 11,
      "upNeigh": 12,
      "downNeigh": 10
    },
    {
      "id": 16,
      "upNeigh": 36,
      "downNeigh": 13
    },
    {
      "id": 20,
      "upNeigh": 21,
      "downNeigh": 18
    },
    {
      "id": 28,
      "upNeigh": 27,
      "downNeigh": 0
    },
    {
      "id": 29,
      "upNeigh": 31,
      "downNeigh": 22
    },
    {
      "id": 33,
      "upNeigh": 32,
      "downNeigh": 35
    },
    {
      "id": 34,
      "upNeigh": 15,
      "downNeigh": 26
    },
    {
      "id": 39,
      "upNeigh": 0,
      "downNeigh": 38
    },
    {
      "id": 40,
      "upNeigh": 0,
      "downNeigh": 23
    },
	{
      "id": 49,
      "upNeigh": 0,
      "downNeigh": 30
    }
  ],
  "points": [
    {
      "id": 4,
      "mainNeigh": 3,
      "mNeigh": 5,
      "pNeigh": 6,
      "reverse": false
    },
    {
      "id": 7,
      "mainNeigh": 17,
      "mNeigh": 8,
      "pNeigh": 10,
      "reverse": false
    },
    {
      "id": 13,
      "mainNeigh": 16,
      "mNeigh": 12,
      "pNeigh": 15,
      "reverse": true
    },
    {
      "id": 21,
      "mainNeigh": 20,
      "mNeigh": 23,
      "pNeigh": 22,
      "reverse": false
    },
    {
      "id": 26,
      "mainNeigh": 34,
      "mNeigh": 25,
      "pNeigh": 27,
      "reverse": true
    },
    {
      "id": 30,
      "mainNeigh": 49,
      "mNeigh": 31,
      "pNeigh": 32,
      "reverse": true
    },
    {
      "id": 36,
      "mainNeigh": 16,
      "mNeigh": 35,
      "pNeigh": 38,
      "reverse": false
    }
  ]
}
